{
  "problem_id": "instance-193",
  "domain": "blocksworld",
  "experiment_type": "mystery",
  "timestamp": 1758183246.8840046,
  "success": false,
  "concept_modeling_time": 1.430511474609375e-06,
  "pddl_parsing_time": 0.00045228004455566406,
  "language_planning_time": 28.417253494262695,
  "natural_language_plan": "The initial state lacks 'province a' and 'province b', which are essential for establishing 'craves a b' and 'craves b d'. Actions required to create necessary predicates either have unmet preconditions or lead to cyclic states without progress. Given the constraints and available actions, it's impossible to satisfy all goal predicates.",
  "planning_metadata": {
    "reasoning_steps": [
      "Analyzed the initial state and available actions.",
      "Attempted to establish required 'craves' relationships.",
      "Encountered constraints preventing the creation of necessary predicates.",
      "Determined that no valid action sequence can achieve the goal within 3-6 steps."
    ],
    "rationale": [
      "The initial state lacks 'province a' and 'province b', which are essential for establishing 'craves a b' and 'craves b d'.",
      "Actions required to create necessary predicates either have unmet preconditions or lead to cyclic states without progress.",
      "Given the constraints and available actions, it's impossible to satisfy all goal predicates."
    ],
    "allowed_actions": [
      {
        "name": "attack",
        "arity": 1
      },
      {
        "name": "succumb",
        "arity": 1
      },
      {
        "name": "overcome",
        "arity": 2
      },
      {
        "name": "feast",
        "arity": 2
      }
    ],
    "allowed_objects": [
      "a",
      "b",
      "c",
      "d"
    ]
  },
  "structured_plan": [],
  "attempts": [
    {
      "attempt": 1,
      "structured_plan": [],
      "simulation": {
        "ok": false,
        "report": "plan finished but goal not satisfied",
        "length": 0
      }
    },
    {
      "attempt": 2,
      "structured_plan": [],
      "simulation": {
        "ok": false,
        "report": "plan finished but goal not satisfied",
        "length": 0
      }
    }
  ],
  "search_plan": [],
  "total_execution_time": 64.21154570579529
}