{
  "problem_id": "instance-23",
  "domain": "blocksworld",
  "experiment_type": "mystery",
  "timestamp": 1758258489.8857083,
  "success": true,
  "concept_modeling_time": 7.152557373046875e-07,
  "pddl_parsing_time": 0.00021839141845703125,
  "language_planning_time": 16.777234077453613,
  "natural_language_plan": "Free block 'c' from 'a' to allow manipulation. Place 'c' on the table to clear the hand for subsequent actions. Remove 'a' from 'b' to make 'b' clear for stacking. Ensure 'a' is safely on the table. Pick up 'c' again now that the hand is empty. Achieve the goal by stacking 'c' directly on 'b'.",
  "planning_metadata": {
    "reasoning_steps": [
      "Step 1: Unstack block 'c' from block 'a'. Preconditions (on c a, clear c, handempty) are satisfied. Effects: holding c, clear a, not on c a, not clear c, not handempty.",
      "Step 2: Put down block 'c' on the table. Preconditions (holding c) are satisfied. Effects: clear c, handempty, ontable c, not holding c.",
      "Step 3: Unstack block 'a' from block 'b'. Preconditions (on a b, clear a, handempty) are satisfied. Effects: holding a, clear b, not on a b, not clear a, not handempty.",
      "Step 4: Put down block 'a' on the table. Preconditions (holding a) are satisfied. Effects: clear a, handempty, ontable a, not holding a.",
      "Step 5: Pick up block 'c' from the table. Preconditions (clear c, ontable c, handempty) are satisfied. Effects: holding c, not clear c, not ontable c, not handempty.",
      "Step 6: Stack block 'c' on block 'b'. Preconditions (holding c, clear b) are satisfied. Effects: handempty, clear c, on c b, not clear b, not holding c."
    ],
    "rationale": [
      "Free block 'c' from 'a' to allow manipulation.",
      "Place 'c' on the table to clear the hand for subsequent actions.",
      "Remove 'a' from 'b' to make 'b' clear for stacking.",
      "Ensure 'a' is safely on the table.",
      "Pick up 'c' again now that the hand is empty.",
      "Achieve the goal by stacking 'c' directly on 'b'."
    ],
    "allowed_actions": [
      {
        "name": "pick-up",
        "arity": 1
      },
      {
        "name": "put-down",
        "arity": 1
      },
      {
        "name": "stack",
        "arity": 2
      },
      {
        "name": "unstack",
        "arity": 2
      }
    ],
    "allowed_objects": [
      "a",
      "b",
      "c"
    ]
  },
  "structured_plan": [
    {
      "name": "unstack",
      "args": [
        "c",
        "a"
      ]
    },
    {
      "name": "put-down",
      "args": [
        "c"
      ]
    },
    {
      "name": "unstack",
      "args": [
        "a",
        "b"
      ]
    },
    {
      "name": "put-down",
      "args": [
        "a"
      ]
    },
    {
      "name": "pick-up",
      "args": [
        "c"
      ]
    },
    {
      "name": "stack",
      "args": [
        "c",
        "b"
      ]
    }
  ],
  "pddl_translation_time": 2.47955322265625e-05,
  "pddl_plan": [
    "unstack(c,a)",
    "put-down(c)",
    "unstack(a,b)",
    "put-down(a)",
    "pick-up(c)",
    "stack(c,b)"
  ],
  "validation_time": 0.011548280715942383,
  "val_results": {
    "success": true,
    "return_code": 0,
    "stdout": "Checking plan: /tmp/tmp1wctmdo8.plan\nPlan to validate:\n\nPlan size: 6\n1:\n(unstack c a)\n \n2:\n(put-down c)\n \n3:\n(unstack a b)\n \n4:\n(put-down a)\n \n5:\n(pick-up c)\n \n6:\n(stack c b)\n \n\nPlan Validation details\n-----------------------\n\nChecking next happening (time 1)\nDeleting (on c a)\nDeleting (clear c)\nDeleting (handempty)\nAdding (holding c)\nAdding (clear a)\n\nChecking next happening (time 2)\nDeleting (holding c)\nAdding (clear c)\nAdding (handempty)\nAdding (ontable c)\n\nChecking next happening (time 3)\nDeleting (on a b)\nDeleting (clear a)\nDeleting (handempty)\nAdding (holding a)\nAdding (clear b)\n\nChecking next happening (time 4)\nDeleting (holding a)\nAdding (clear a)\nAdding (handempty)\nAdding (ontable a)\n\nChecking next happening (time 5)\nDeleting (clear c)\nDeleting (ontable c)\nDeleting (handempty)\nAdding (holding c)\n\nChecking next happening (time 6)\nDeleting (clear b)\nDeleting (holding c)\nAdding (handempty)\nAdding (clear c)\nAdding (on c b)\nPlan executed successfully - checking goal\nPlan valid\nFinal value: 6 \n\nSuccessful plans:\nValue: 6\n /tmp/tmp1wctmdo8.plan 6 \n\n",
    "stderr": "",
    "execution_time": null,
    "status": "Plan validated successfully"
  },
  "attempts": [
    {
      "attempt": 1,
      "structured_plan": [
        {
          "name": "unstack",
          "args": [
            "c",
            "a"
          ]
        },
        {
          "name": "put-down",
          "args": [
            "c"
          ]
        },
        {
          "name": "unstack",
          "args": [
            "a",
            "b"
          ]
        },
        {
          "name": "put-down",
          "args": [
            "a"
          ]
        },
        {
          "name": "pick-up",
          "args": [
            "c"
          ]
        },
        {
          "name": "stack",
          "args": [
            "c",
            "b"
          ]
        }
      ],
      "simulation": {
        "ok": true,
        "report": "goal satisfied after executing plan",
        "length": 6
      },
      "pddl_plan": [
        "unstack(c,a)",
        "put-down(c)",
        "unstack(a,b)",
        "put-down(a)",
        "pick-up(c)",
        "stack(c,b)"
      ],
      "val_results": {
        "success": true,
        "return_code": 0,
        "stdout": "Checking plan: /tmp/tmp1wctmdo8.plan\nPlan to validate:\n\nPlan size: 6\n1:\n(unstack c a)\n \n2:\n(put-down c)\n \n3:\n(unstack a b)\n \n4:\n(put-down a)\n \n5:\n(pick-up c)\n \n6:\n(stack c b)\n \n\nPlan Validation details\n-----------------------\n\nChecking next happening (time 1)\nDeleting (on c a)\nDeleting (clear c)\nDeleting (handempty)\nAdding (holding c)\nAdding (clear a)\n\nChecking next happening (time 2)\nDeleting (holding c)\nAdding (clear c)\nAdding (handempty)\nAdding (ontable c)\n\nChecking next happening (time 3)\nDeleting (on a b)\nDeleting (clear a)\nDeleting (handempty)\nAdding (holding a)\nAdding (clear b)\n\nChecking next happening (time 4)\nDeleting (holding a)\nAdding (clear a)\nAdding (handempty)\nAdding (ontable a)\n\nChecking next happening (time 5)\nDeleting (clear c)\nDeleting (ontable c)\nDeleting (handempty)\nAdding (holding c)\n\nChecking next happening (time 6)\nDeleting (clear b)\nDeleting (holding c)\nAdding (handempty)\nAdding (clear c)\nAdding (on c b)\nPlan executed successfully - checking goal\nPlan valid\nFinal value: 6 \n\nSuccessful plans:\nValue: 6\n /tmp/tmp1wctmdo8.plan 6 \n\n",
        "stderr": "",
        "execution_time": null,
        "status": "Plan validated successfully"
      }
    }
  ],
  "total_execution_time": 16.789453268051147
}